[{"picture":"img/Bavarskaya.png","calories":null,"price":null,"ingr":[0,1,9],"title":"Баварская"},{"picture":"img/Derevenskaya.png","calories":null,"price":null,"ingr":[3,4,2,5,9],"title":"Деревенская"},{"picture":"img/Leonardo.png","calories":null,"price":null,"ingr":[10,2,3,0,11],"title":"Леонардо"},{"picture":"img/Pepperony.png","calories":null,"price":null,"ingr":[0,11,2],"title":"Пепперони"},{"picture":"img/Tango.png","calories":null,"price":null,"ingr":[2,7,8,6,5],"title":"Танго"},{"picture":"img/Flamenco.png","calories":null,"price":null,"ingr":[8,2],"title":"Фламенко"},{"picture":"img/pizza-margarita.jpg","calories":null,"price":null,"ingr":[1,13,12,14],"title":"Маргаритта"},{"picture":"img/Техас.jpg","calories":null,"price":null,"ingr":[4,10,15,3,9],"title":"Техас"},{"picture":"img/барбекю.jpg","calories":null,"price":null,"ingr":[17,10,16,15,1,9],"title":"Барбекю"},{"picture":"img/американа.jpg","calories":null,"price":null,"ingr":[16,6,1,0],"title":"Американа"},{"picture":"img/гавайская.jpg","calories":null,"price":null,"ingr":[17,18,1],"title":"Гавайская"},{"picture":"img/кантри.jpg","calories":null,"price":null,"ingr":[10,16,6,15,1,19],"title":"Кантри"},{"picture":"img/карбонара.jpg","calories":null,"price":null,"ingr":[10,16,6,15,1],"title":"Карбонара"},{"picture":"img/SalmonPhill.jpg","calories":null,"price":null,"ingr":[1,2,9,20],"title":"Лосось Филадельфия"}]